DemoPackage/__init__.py
DemoPackage/__main__.py
DemoPackage/daily_planner.py
DemoPackage/furtune_cookie.py
DemoPackage/generate_emoji.py
DemoPackage/owl_banner.py
DemoPackage/password_strength.py
demopackage_cs467-0.1.3.dist-info/LICENSE
demopackage_cs467-0.1.3.dist-info/METADATA
demopackage_cs467-0.1.3.dist-info/WHEEL
demopackage_cs467-0.1.3.dist-info/entry_points.txt
demopackage_cs467-0.1.3.dist-info/top_level.txt
demopackage_cs467-0.1.3.dist-info/RECORD
