Metadata-Version: 2.2
Name: demopackage-cs467
Version: 0.1.3
Summary: A fun Python package that enhances developer workflows with banners, random fortunes, emojis, a daily planner, and a password strength checker.
Author-email: Polaris Wu <sw5693@nyu.edu>, Michael Liu <gl2362@nyu.edu>, Felix Guo <tg2490@nyu.edu>, Jiangbo Shen <js12154@nyu.edu>
License:                     GNU GENERAL PUBLIC LICENSE
Project-URL: Homepage, https://github.com/software-students-spring2025/3-python-package-cs467
Project-URL: Repository, https://github.com/software-students-spring2025/3-python-package-cs467.git
Project-URL: Bug Tracker, https://github.com/software-students-spring2025/3-python-package-cs467/issues
Keywords: python,package,build,tutorial
Classifier: Programming Language :: Python :: 3
Classifier: Programming Language :: Python :: 3.8
Classifier: Programming Language :: Python :: 3.9
Classifier: Programming Language :: Python :: 3.10
Classifier: Intended Audience :: Education
Classifier: License :: OSI Approved :: GNU General Public License v3 (GPLv3)
Classifier: Operating System :: OS Independent
Requires-Python: >=3.7
License-File: LICENSE
Provides-Extra: dev
Requires-Dist: pytest; extra == "dev"
